README.md
pyproject.toml
setup.py
deeporigin_datahub_sdk.egg-info/PKG-INFO
deeporigin_datahub_sdk.egg-info/SOURCES.txt
deeporigin_datahub_sdk.egg-info/dependency_links.txt
deeporigin_datahub_sdk.egg-info/requires.txt
deeporigin_datahub_sdk.egg-info/top_level.txt
do_sdk_datahub/__init__.py
do_sdk_datahub/client.py
do_sdk_datahub/errors.py
do_sdk_datahub/py.typed
do_sdk_datahub/types.py
do_sdk_datahub/api/__init__.py
do_sdk_datahub/api/default/__init__.py
do_sdk_datahub/api/default/add_database_column.py
do_sdk_datahub/api/default/archive_files.py
do_sdk_datahub/api/default/configure_column_select_options.py
do_sdk_datahub/api/default/convert_id_format.py
do_sdk_datahub/api/default/create_chat_thread.py
do_sdk_datahub/api/default/create_database.py
do_sdk_datahub/api/default/create_file_download_url.py
do_sdk_datahub/api/default/create_file_upload.py
do_sdk_datahub/api/default/create_workspace.py
do_sdk_datahub/api/default/delete_database.py
do_sdk_datahub/api/default/delete_database_column.py
do_sdk_datahub/api/default/delete_rows.py
do_sdk_datahub/api/default/delete_workspace.py
do_sdk_datahub/api/default/describe_code_execution.py
do_sdk_datahub/api/default/describe_database.py
do_sdk_datahub/api/default/describe_database_stats.py
do_sdk_datahub/api/default/describe_file.py
do_sdk_datahub/api/default/describe_row.py
do_sdk_datahub/api/default/describe_workspace.py
do_sdk_datahub/api/default/download_file.py
do_sdk_datahub/api/default/ensure_rows.py
do_sdk_datahub/api/default/execute_code.py
do_sdk_datahub/api/default/execute_code_sync.py
do_sdk_datahub/api/default/get_code_execution_result.py
do_sdk_datahub/api/default/import_rows.py
do_sdk_datahub/api/default/list_chat_thread_messages.py
do_sdk_datahub/api/default/list_database_column_unique_values_v2.py
do_sdk_datahub/api/default/list_database_rows.py
do_sdk_datahub/api/default/list_files.py
do_sdk_datahub/api/default/list_mentions.py
do_sdk_datahub/api/default/list_row_back_references.py
do_sdk_datahub/api/default/list_rows.py
do_sdk_datahub/api/default/lock_database.py
do_sdk_datahub/api/default/parse_base_sequence_data.py
do_sdk_datahub/api/default/send_chat_message.py
do_sdk_datahub/api/default/unlock_database.py
