Metadata-Version: 2.1
Name: deeporigin-datahub-sdk
Version: 0.1.1
Summary: A client library for accessing Deep Origin Data Management API
Requires-Python: >=3.8, <4
Requires-Dist: httpx<0.28.0,>=0.20.0
Requires-Dist: attrs>=21.3.0
Requires-Dist: python-dateutil<3,>=2.8.0
